{ 
        "payType": {
                "sort-1": {
                        "name":"微信",
                        "color":"red"
                },
                "sort-2":{
                        "name": "支付宝",
                        "color":"red"
                },
                "sort-0": {
                        "name":"刷卡",
                        "color":"red"
                },
                "sort-3": {
                        "name":"银联二维码",
                        "color":"red"
                }
        },
        "outMoneyStatus": {
                "sort-": {
                       "name": "全部",
                       "color":"#E6A23C"
                },
                "sort-1":{
                        "name": "待结算",
                        "color":"#E6A23C"
                },
                "sort-2": {
                        "name":"结算初步审核通过",
                        "color":"#48af12"
                },
                "sort-03": {
                        "name":"复核通过",
                        "color":"#48af12"
                },
                "sort-4": {
                        "name":"处理成功",
                        "color":"#48af12"
                },
                "sort-06":{
                        "name": "出款发送中",
                        "color":"#E6A23C"
                },
                "sort-11": {
                        "name":"初步审核不通过",
                        "color":"#E6A23C"
                },
                "sort-22": {
                        "name":"复核不通过",
                        "color":"#E6A23C"
                },
                "sort-33": {
                        "name":"不出款",
                        "color":"#E6A23C"
                },
                "sort-44": {
                        "name":"处理失败",
                        "color":"#ff5b5b"
                },
                "sort-55": {
                        "name":"出款已发送",
                        "color":"#E6A23C"
                },
                "sort-77": {
                        "name":"已重出",
                        "color":"#E6A23C"
                }
        },
        "settTypes":{
                "": {
                        "name": "全部",
                        "color":"#E6A23C"
                }
        }
}